maldisc/__init__.py
maldisc/__main__.py
maldisc/anime.py
maldisc/constants.py
maldisc/exceptions.py
maldisc/jikanrequests.py
maldisc/logging_.py
maldisc-0.1.0a1.dist-info/LICENSE
maldisc-0.1.0a1.dist-info/METADATA
maldisc-0.1.0a1.dist-info/WHEEL
maldisc-0.1.0a1.dist-info/entry_points.txt
maldisc-0.1.0a1.dist-info/top_level.txt
maldisc-0.1.0a1.dist-info/RECORD
